Workbook

Sheet Orders_raw
A1: order_id | B1: customer_id | C1: Customer_Name | D1: order_date | E1: Month | F1: Product_Name | G1: Category | H1: quantity | I1: unit_price | J1: Total_Price | K1: Order_Type | L1: Payment_Method
A2: 5000 | B2: 53 | C2: =IFERROR(_xlfn.XLOOKUP(B2, Customers_raw!A:A, Customers_raw!B:B), "Unknown Customer") -> John Thomas | D2: 45972 | E2: =TEXT(D:D,"YYYY-MM") -> 2025-11 | F2: Memory Foam Pillow | G2: Bedding | H2: 3 | I2: 32 | J2: =H2*I2 -> 96 | K2: =IF(H2<0,"Return","Sale") -> Sale | L2: Paypal
A3: 5001 | B3: 17 | C3: =IFERROR(_xlfn.XLOOKUP(B3, Customers_raw!A:A, Customers_raw!B:B), "Unknown Customer") -> Mary Thomas | D3: 45899 | E3: =TEXT(D:D,"YYYY-MM") -> 2025-08 | F3: Wall Mirror | G3: Home Decor | H3: 1 | I3: 65 | J3: =H3*I3 -> 65 | K3: =IF(H3<0,"Return","Sale") -> Sale | L3: Debit Card
A4: 5002 | B4: 95 | C4: =IFERROR(_xlfn.XLOOKUP(B4, Customers_raw!A:A, Customers_raw!B:B), "Unknown Customer") -> Michelle Martin | D4: 45791 | E4: =TEXT(D:D,"YYYY-MM") -> 2025-05 | F4: Ceramic Mug Set | G4: Kitchen | H4: 3 | I4: 24 | J4: =H4*I4 -> 72 | K4: =IF(H4<0,"Return","Sale") -> Sale | L4: Paypal
A5: 5003 | B5: 86 | C5: =IFERROR(_xlfn.XLOOKUP(B5, Customers_raw!A:A, Customers_raw!B:B), "Unknown Customer") -> Steven Jones | D5: 45719 | E5: =TEXT(D:D,"YYYY-MM") -> 2025-03 | F5: Cotton Bedsheet Set | G5: Bedding | H5: 3 | I5: 55 | J5: =H5*I5 -> 165 | K5: =IF(H5<0,"Return","Sale") -> Sale | L5: Paypal
A6: 5004 | B6: 104 | C6: =IFERROR(_xlfn.XLOOKUP(B6, Customers_raw!A:A, Customers_raw!B:B), "Unknown Customer") -> Christopher Brown | D6: 45939 | E6: =TEXT(D:D,"YYYY-MM") -> 2025-10 | F6: Memory Foam Pillow | G6: Bedding | H6: 2 | I6: 32 | J6: =H6*I6 -> 64 | K6: =IF(H6<0,"Return","Sale") -> Sale | L6: Paypal
A7: 5005 | B7: 71 | C7: =IFERROR(_xlfn.XLOOKUP(B7, Customers_raw!A:A, Customers_raw!B:B), "Unknown Customer") -> Barbara Rodriguez | D7: 45782 | E7: =TEXT(D:D,"YYYY-MM") -> 2025-05 | F7: Table Lamp | G7: Lighting | H7: 1 | I7: 45 | J7: =H7*I7 -> 45 | K7: =IF(H7<0,"Return","Sale") -> Sale | L7: Debit Card
A8: 5006 | B8: 31 | C8: =IFERROR(_xlfn.XLOOKUP(B8, Customers_raw!A:A, Customers_raw!B:B), "Unknown Customer") -> Nancy Harris | D8: 45790 | E8: =TEXT(D:D,"YYYY-MM") -> 2025-05 | F8: String Lights | G8: Lighting | H8: 1 | I8: 18 | J8: =H8*I8 -> 18 | K8: =IF(H8<0,"Return","Sale") -> Sale | L8: Debit Card
A9: 5007 | B9: 68 | C9: =IFERROR(_xlfn.XLOOKUP(B9, Customers_raw!A:A, Customers_raw!B:B), "Unknown Customer") -> James Hernandez | D9: 45998 | E9: =TEXT(D:D,"YYYY-MM") -> 2025-12 | F9: Table Lamp | G9: Lighting | H9: 1 | I9: 42 | J9: =H9*I9 -> 42 | K9: =IF(H9<0,"Return","Sale") -> Sale | L9: Paypal
A10: 5008 | B10: 47 | C10: =IFERROR(_xlfn.XLOOKUP(B10, Customers_raw!A:A, Customers_raw!B:B), "Unknown Customer") -> Christopher Rodriguez | D10: 46009 | E10: =TEXT(D:D,"YYYY-MM") -> 2025-12 | F10: Wall Mirror | G10: Home Decor | H10: 1 | I10: 65 | J10: =H10*I10 -> 65 | K10: =IF(H10<0,"Return","Sale") -> Sale | L10: Credit Card
A11: 5009 | B11: 83 | C11: =IFERROR(_xlfn.XLOOKUP(B11, Customers_raw!A:A, Customers_raw!B:B), "Unknown Customer") -> Mary Martinez | D11: 45938 | E11: =TEXT(D:D,"YYYY-MM") -> 2025-10 | F11: Memory Foam Pillow | G11: Bedding | H11: 1 | I11: 32 | J11: =H11*I11 -> 32 | K11: =IF(H11<0,"Return","Sale") -> Sale | L11: Debit Card
A12: 5010 | B12: 98 | C12: =IFERROR(_xlfn.XLOOKUP(B12, Customers_raw!A:A, Customers_raw!B:B), "Unknown Customer") -> Karen Williams | D12: 45958 | E12: =TEXT(D:D,"YYYY-MM") -> 2025-10 | F12: Memory Foam Pillow | G12: Bedding | H12: 1 | I12: 29 | J12: =H12*I12 -> 29 | K12: =IF(H12<0,"Return","Sale") -> Sale | L12: Credit Card
A13: 5011 | B13: 32 | C13: =IFERROR(_xlfn.XLOOKUP(B13, Customers_raw!A:A, Customers_raw!B:B), "Unknown Customer") -> Kimberly Lopez | D13: 45772 | E13: =TEXT(D:D,"YYYY-MM") -> 2025-04 | F13: Throw Pillow | G13: Home Decor | H13: 1 | I13: 25 | J13: =H13*I13 -> 25 | K13: =IF(H13<0,"Return","Sale") -> Sale | L13: Debit Card
... A429: 5427 | B429: 84 | C429: =IFERROR(_xlfn.XLOOKUP(B429, Customers_raw!A:A, Customers_raw!B:B), "Unknown Customer") -> Kimberly Lewis | D429: 45836 | E429: =TEXT(D:D,"YYYY-MM") -> 2025-06 | F429: Cutting Board | G429: Kitchen | H429: 2 | I429: 19 | J429: =H429*I429 -> 38 | K429: =IF(H429<0,"Return","Sale") -> Sale | L429: Debit Card
A430: 5428 | B430: Unknown | C430: =IFERROR(_xlfn.XLOOKUP(B430, Customers_raw!A:A, Customers_raw!B:B), "Unknown Customer") -> Unknown Customer | D430: 45896 | E430: =TEXT(D:D,"YYYY-MM") -> 2025-08 | F430: Ceramic Vase | G430: Home Decor | H430: 2 | I430: 28 | J430: =H430*I430 -> 56 | K430: =IF(H430<0,"Return","Sale") -> Sale | L430: Debit Card
A431: 5429 | B431: 76 | C431: =IFERROR(_xlfn.XLOOKUP(B431, Customers_raw!A:A, Customers_raw!B:B), "Unknown Customer") -> Thomas Anderson | D431: 45993 | E431: =TEXT(D:D,"YYYY-MM") -> 2025-12 | F431: Wool Blanket | G431: Bedding | H431: 1 | I431: 70 | J431: =H431*I431 -> 70 | K431: =IF(H431<0,"Return","Sale") -> Sale | L431: Paypal
A432: 5430 | B432: 76 | C432: =IFERROR(_xlfn.XLOOKUP(B432, Customers_raw!A:A, Customers_raw!B:B), "Unknown Customer") -> Thomas Anderson | D432: 45945 | E432: =TEXT(D:D,"YYYY-MM") -> 2025-10 | F432: Memory Foam Pillow | G432: Bedding | H432: 2 | I432: 35 | J432: =H432*I432 -> 70 | K432: =IF(H432<0,"Return","Sale") -> Sale | L432: Credit Card
A433: 5431 | B433: 85 | C433: =IFERROR(_xlfn.XLOOKUP(B433, Customers_raw!A:A, Customers_raw!B:B), "Unknown Customer") -> Elizabeth Martinez | D433: 45978 | E433: =TEXT(D:D,"YYYY-MM") -> 2025-11 | F433: Cotton Bedsheet Set | G433: Bedding | H433: 2 | I433: 55 | J433: =H433*I433 -> 110 | K433: =IF(H433<0,"Return","Sale") -> Sale | L433: Debit Card
A434: 5432 | B434: 87 | C434: =IFERROR(_xlfn.XLOOKUP(B434, Customers_raw!A:A, Customers_raw!B:B), "Unknown Customer") -> Joseph Williams | D434: 45820 | E434: =TEXT(D:D,"YYYY-MM") -> 2025-06 | F434: String Lights | G434: Lighting | H434: 1 | I434: 15 | J434: =H434*I434 -> 15 | K434: =IF(H434<0,"Return","Sale") -> Sale | L434: Paypal
A435: 5433 | B435: 3 | C435: =IFERROR(_xlfn.XLOOKUP(B435, Customers_raw!A:A, Customers_raw!B:B), "Unknown Customer") -> Anthony Williams | D435: 45666 | E435: =TEXT(D:D,"YYYY-MM") -> 2025-01 | F435: Throw Pillow | G435: Home Decor | H435: 2 | I435: 25 | J435: =H435*I435 -> 50 | K435: =IF(H435<0,"Return","Sale") -> Sale | L435: Paypal
A436: 5434 | B436: 43 | C436: =IFERROR(_xlfn.XLOOKUP(B436, Customers_raw!A:A, Customers_raw!B:B), "Unknown Customer") -> Sandra Clark | D436: 45767 | E436: =TEXT(D:D,"YYYY-MM") -> 2025-04 | F436: Wool Blanket | G436: Bedding | H436: 1 | I436: 70 | J436: =H436*I436 -> 70 | K436: =IF(H436<0,"Return","Sale") -> Sale | L436: Debit Card
A437: 5435 | B437: 43 | C437: =IFERROR(_xlfn.XLOOKUP(B437, Customers_raw!A:A, Customers_raw!B:B), "Unknown Customer") -> Sandra Clark | D437: 45796 | E437: =TEXT(D:D,"YYYY-MM") -> 2025-05 | F437: Throw Pillow | G437: Home Decor | H437: 3 | I437: 22 | J437: =H437*I437 -> 66 | K437: =IF(H437<0,"Return","Sale") -> Sale | L437: Credit Card
A438: 5436 | B438: 28 | C438: =IFERROR(_xlfn.XLOOKUP(B438, Customers_raw!A:A, Customers_raw!B:B), "Unknown Customer") -> Michael Lopez | D438: 45979 | E438: =TEXT(D:D,"YYYY-MM") -> 2025-11 | F438: Ceramic Mug Set | G438: Kitchen | H438: 2 | I438: 24 | J438: =H438*I438 -> 48 | K438: =IF(H438<0,"Return","Sale") -> Sale | L438: Debit Card
A439: 5437 | B439: 20 | C439: =IFERROR(_xlfn.XLOOKUP(B439, Customers_raw!A:A, Customers_raw!B:B), "Unknown Customer") -> David Ramirez | D439: 45743 | E439: =TEXT(D:D,"YYYY-MM") -> 2025-03 | F439: String Lights | G439: Lighting | H439: 1 | I439: 21 | J439: =H439*I439 -> 21 | K439: =IF(H439<0,"Return","Sale") -> Sale | L439: Credit Card
A440: 5438 | B440: 41 | C440: =IFERROR(_xlfn.XLOOKUP(B440, Customers_raw!A:A, Customers_raw!B:B), "Unknown Customer") -> Margaret Clark | D440: 45968 | E440: =TEXT(D:D,"YYYY-MM") -> 2025-11 | F440: Wool Blanket | G440: Bedding | H440: 1 | I440: 70 | J440: =H440*I440 -> 70 | K440: =IF(H440<0,"Return","Sale") -> Sale | L440: Credit Card
A441: 5439 | B441: 110 | C441: =IFERROR(_xlfn.XLOOKUP(B441, Customers_raw!A:A, Customers_raw!B:B), "Unknown Customer") -> Betty Walker | D441: 45711 | E441: =TEXT(D:D,"YYYY-MM") -> 2025-02 | F441: Wall Mirror | G441: Home Decor | H441: 1 | I441: 68 | J441: =H441*I441 -> 68 | K441: =IF(H441<0,"Return","Sale") -> Sale | L441: Debit Card
A442: 5440 | B442: 46 | C442: =IFERROR(_xlfn.XLOOKUP(B442, Customers_raw!A:A, Customers_raw!B:B), "Unknown Customer") -> Mary Rodriguez | D442: 45709 | E442: =TEXT(D:D,"YYYY-MM") -> 2025-02 | F442: Ceramic Mug Set | G442: Kitchen | H442: 1 | I442: 24 | J442: =H442*I442 -> 24 | K442: =IF(H442<0,"Return","Sale") -> Sale | L442: Credit Card
... A724: 5722 | B724: 52 | C724: =IFERROR(_xlfn.XLOOKUP(B724, Customers_raw!A:A, Customers_raw!B:B), "Unknown Customer") -> Sarah Johnson | D724: 45740 | E724: =TEXT(D:D,"YYYY-MM") -> 2025-03 | F724: Ceramic Vase | G724: Home Decor | H724: 3 | I724: 31 | J724: =H724*I724 -> 93 | K724: =IF(H724<0,"Return","Sale") -> Sale | L724: Credit Card
A725: 5723 | B725: Unknown | C725: =IFERROR(_xlfn.XLOOKUP(B725, Customers_raw!A:A, Customers_raw!B:B), "Unknown Customer") -> Unknown Customer | D725: 45746 | E725: =TEXT(D:D,"YYYY-MM") -> 2025-03 | F725: Table Lamp | G725: Lighting | H725: 1 | I725: 45 | J725: =H725*I725 -> 45 | K725: =IF(H725<0,"Return","Sale") -> Sale | L725: Credit Card
A726: 5724 | B726: 49 | C726: =IFERROR(_xlfn.XLOOKUP(B726, Customers_raw!A:A, Customers_raw!B:B), "Unknown Customer") -> Steven Smith | D726: 45822 | E726: =TEXT(D:D,"YYYY-MM") -> 2025-06 | F726: Table Lamp | G726: Lighting | H726: 3 | I726: 42 | J726: =H726*I726 -> 126 | K726: =IF(H726<0,"Return","Sale") -> Sale | L726: Paypal
A727: 5725 | B727: 70 | C727: =IFERROR(_xlfn.XLOOKUP(B727, Customers_raw!A:A, Customers_raw!B:B), "Unknown Customer") -> Karen Perez | D727: 45692 | E727: =TEXT(D:D,"YYYY-MM") -> 2025-02 | F727: Wall Mirror | G727: Home Decor | H727: 3 | I727: 65 | J727: =H727*I727 -> 195 | K727: =IF(H727<0,"Return","Sale") -> Sale | L727: Debit Card
A728: 5726 | B728: 79 | C728: =IFERROR(_xlfn.XLOOKUP(B728, Customers_raw!A:A, Customers_raw!B:B), "Unknown Customer") -> Nancy Jackson | D728: 45759 | E728: =TEXT(D:D,"YYYY-MM") -> 2025-04 | F728: Wall Mirror | G728: Home Decor | H728: 1 | I728: 68 | J728: =H728*I728 -> 68 | K728: =IF(H728<0,"Return","Sale") -> Sale | L728: Debit Card
A729: 5727 | B729: 62 | C729: =IFERROR(_xlfn.XLOOKUP(B729, Customers_raw!A:A, Customers_raw!B:B), "Unknown Customer") -> Mary Wilson | D729: 45973 | E729: =TEXT(D:D,"YYYY-MM") -> 2025-11 | F729: Cutting Board | G729: Kitchen | H729: 1 | I729: 19 | J729: =H729*I729 -> 19 | K729: =IF(H729<0,"Return","Sale") -> Sale | L729: Debit Card
A730: 5728 | B730: 26 | C730: =IFERROR(_xlfn.XLOOKUP(B730, Customers_raw!A:A, Customers_raw!B:B), "Unknown Customer") -> Betty Johnson | D730: 45973 | E730: =TEXT(D:D,"YYYY-MM") -> 2025-11 | F730: Wool Blanket | G730: Bedding | H730: 3 | I730: 70 | J730: =H730*I730 -> 210 | K730: =IF(H730<0,"Return","Sale") -> Sale | L730: Paypal
A731: 5729 | B731: 17 | C731: =IFERROR(_xlfn.XLOOKUP(B731, Customers_raw!A:A, Customers_raw!B:B), "Unknown Customer") -> Mary Thomas | D731: 45939 | E731: =TEXT(D:D,"YYYY-MM") -> 2025-10 | F731: String Lights | G731: Lighting | H731: 2 | I731: 18 | J731: =H731*I731 -> 36 | K731: =IF(H731<0,"Return","Sale") -> Sale | L731: Credit Card
A732: 5730 | B732: 79 | C732: =IFERROR(_xlfn.XLOOKUP(B732, Customers_raw!A:A, Customers_raw!B:B), "Unknown Customer") -> Nancy Jackson | D732: 45674 | E732: =TEXT(D:D,"YYYY-MM") -> 2025-01 | F732: Non-Stick Pan Set | G732: Kitchen | H732: -1 | I732: 57 | J732: =H732*I732 -> -57 | K732: =IF(H732<0,"Return","Sale") -> Return | L732: Credit Card
A733: 5731 | B733: 80 | C733: =IFERROR(_xlfn.XLOOKUP(B733, Customers_raw!A:A, Customers_raw!B:B), "Unknown Customer") -> Susan Lopez | D733: 45883 | E733: =TEXT(D:D,"YYYY-MM") -> 2025-08 | F733: Table Lamp | G733: Lighting | H733: 3 | I733: 45 | J733: =H733*I733 -> 135 | K733: =IF(H733<0,"Return","Sale") -> Sale | L733: Paypal
A734: 5732 | B734: 26 | C734: =IFERROR(_xlfn.XLOOKUP(B734, Customers_raw!A:A, Customers_raw!B:B), "Unknown Customer") -> Betty Johnson | D734: 45982 | E734: =TEXT(D:D,"YYYY-MM") -> 2025-11 | F734: String Lights | G734: Lighting | H734: 2 | I734: 15 | J734: =H734*I734 -> 30 | K734: =IF(H734<0,"Return","Sale") -> Sale | L734: Debit Card
A735: 5733 | B735: 9 | C735: =IFERROR(_xlfn.XLOOKUP(B735, Customers_raw!A:A, Customers_raw!B:B), "Unknown Customer") -> Andrew Anderson | D735: 45669 | E735: =TEXT(D:D,"YYYY-MM") -> 2025-01 | F735: Throw Pillow | G735: Home Decor | H735: 1 | I735: 22 | J735: =H735*I735 -> 22 | K735: =IF(H735<0,"Return","Sale") -> Sale | L735: Debit Card
A736: 5734 | B736: 36 | C736: =IFERROR(_xlfn.XLOOKUP(B736, Customers_raw!A:A, Customers_raw!B:B), "Unknown Customer") -> Daniel Harris | D736: 45702 | E736: =TEXT(D:D,"YYYY-MM") -> 2025-02 | F736: Floor Lamp | G736: Lighting | H736: 2 | I736: 92 | J736: =H736*I736 -> 184 | K736: =IF(H736<0,"Return","Sale") -> Sale | L736: Credit Card
A737: 5735 | B737: 94 | C737: =IFERROR(_xlfn.XLOOKUP(B737, Customers_raw!A:A, Customers_raw!B:B), "Unknown Customer") -> Kenneth Jones | D737: 45774 | E737: =TEXT(D:D,"YYYY-MM") -> 2025-04 | F737: Floor Lamp | G737: Lighting | H737: 1 | I737: 92 | J737: =H737*I737 -> 92 | K737: =IF(H737<0,"Return","Sale") -> Sale | L737: Credit Card
... A904: 5902 | B904: 9 | C904: =IFERROR(_xlfn.XLOOKUP(B904, Customers_raw!A:A, Customers_raw!B:B), "Unknown Customer") -> Andrew Anderson | D904: 45968 | E904: =TEXT(D:D,"YYYY-MM") -> 2025-11 | F904: String Lights | G904: Lighting | H904: 1 | I904: 18 | J904: =H904*I904 -> 18 | K904: =IF(H904<0,"Return","Sale") -> Sale | L904: Debit Card
A905: 5903 | B905: Unknown | C905: =IFERROR(_xlfn.XLOOKUP(B905, Customers_raw!A:A, Customers_raw!B:B), "Unknown Customer") -> Unknown Customer | D905: 45675 | E905: =TEXT(D:D,"YYYY-MM") -> 2025-01 | F905: String Lights | G905: Lighting | H905: 1 | I905: 18 | J905: =H905*I905 -> 18 | K905: =IF(H905<0,"Return","Sale") -> Sale | L905: Paypal
A906: 5904 | B906: 90 | C906: =IFERROR(_xlfn.XLOOKUP(B906, Customers_raw!A:A, Customers_raw!B:B), "Unknown Customer") -> John Harris | D906: 45932 | E906: =TEXT(D:D,"YYYY-MM") -> 2025-10 | F906: Floor Lamp | G906: Lighting | H906: 2 | I906: 89 | J906: =H906*I906 -> 178 | K906: =IF(H906<0,"Return","Sale") -> Sale | L906: Credit Card
A907: 5905 | B907: 101 | C907: =IFERROR(_xlfn.XLOOKUP(B907, Customers_raw!A:A, Customers_raw!B:B), "Unknown Customer") -> David Lee | D907: 45737 | E907: =TEXT(D:D,"YYYY-MM") -> 2025-03 | F907: Cutting Board | G907: Kitchen | H907: 1 | I907: 19.095238 | J907: =H907*I907 -> 19.095238 | K907: =IF(H907<0,"Return","Sale") -> Sale | L907: Paypal
A908: 5906 | B908: 25 | C908: =IFERROR(_xlfn.XLOOKUP(B908, Customers_raw!A:A, Customers_raw!B:B), "Unknown Customer") -> Emily Wilson | D908: 45725 | E908: =TEXT(D:D,"YYYY-MM") -> 2025-03 | F908: Memory Foam Pillow | G908: Bedding | H908: 3 | I908: 32 | J908: =H908*I908 -> 96 | K908: =IF(H908<0,"Return","Sale") -> Sale | L908: Debit Card
A909: 5907 | B909: 52 | C909: =IFERROR(_xlfn.XLOOKUP(B909, Customers_raw!A:A, Customers_raw!B:B), "Unknown Customer") -> Sarah Johnson | D909: 45860 | E909: =TEXT(D:D,"YYYY-MM") -> 2025-07 | F909: Memory Foam Pillow | G909: Bedding | H909: 1 | I909: 29 | J909: =H909*I909 -> 29 | K909: =IF(H909<0,"Return","Sale") -> Sale | L909: Paypal
A910: 5908 | B910: 68 | C910: =IFERROR(_xlfn.XLOOKUP(B910, Customers_raw!A:A, Customers_raw!B:B), "Unknown Customer") -> James Hernandez | D910: 46007 | E910: =TEXT(D:D,"YYYY-MM") -> 2025-12 | F910: String Lights | G910: Lighting | H910: 2 | I910: 18 | J910: =H910*I910 -> 36 | K910: =IF(H910<0,"Return","Sale") -> Sale | L910: Debit Card
A911: 5909 | B911: 90 | C911: =IFERROR(_xlfn.XLOOKUP(B911, Customers_raw!A:A, Customers_raw!B:B), "Unknown Customer") -> John Harris | D911: 45920 | E911: =TEXT(D:D,"YYYY-MM") -> 2025-09 | F911: Memory Foam Pillow | G911: Bedding | H911: 1 | I911: 32 | J911: =H911*I911 -> 32 | K911: =IF(H911<0,"Return","Sale") -> Sale | L911: Debit Card
A912: 5910 | B912: 99 | C912: =IFERROR(_xlfn.XLOOKUP(B912, Customers_raw!A:A, Customers_raw!B:B), "Unknown Customer") -> Steven Thomas | D912: 45793 | E912: =TEXT(D:D,"YYYY-MM") -> 2025-05 | F912: Wool Blanket | G912: Bedding | H912: 1 | I912: 70 | J912: =H912*I912 -> 70 | K912: =IF(H912<0,"Return","Sale") -> Sale | L912: Debit Card
A913: 5911 | B913: 12 | C913: =IFERROR(_xlfn.XLOOKUP(B913, Customers_raw!A:A, Customers_raw!B:B), "Unknown Customer") -> Linda Moore | D913: 45713 | E913: =TEXT(D:D,"YYYY-MM") -> 2025-02 | F913: Table Lamp | G913: Lighting | H913: 2 | I913: 45 | J913: =H913*I913 -> 90 | K913: =IF(H913<0,"Return","Sale") -> Sale | L913: Unknown
A914: 5912 | B914: 106 | C914: =IFERROR(_xlfn.XLOOKUP(B914, Customers_raw!A:A, Customers_raw!B:B), "Unknown Customer") -> Thomas Lopez | D914: 45835 | E914: =TEXT(D:D,"YYYY-MM") -> 2025-06 | F914: Floor Lamp | G914: Lighting | H914: 3 | I914: 92 | J914: =H914*I914 -> 276 | K914: =IF(H914<0,"Return","Sale") -> Sale | L914: Paypal
A915: 5913 | B915: 6 | C915: =IFERROR(_xlfn.XLOOKUP(B915, Customers_raw!A:A, Customers_raw!B:B), "Unknown Customer") -> David Martinez | D915: 45742 | E915: =TEXT(D:D,"YYYY-MM") -> 2025-03 | F915: Ceramic Vase | G915: Home Decor | H915: 2 | I915: 25 | J915: =H915*I915 -> 50 | K915: =IF(H915<0,"Return","Sale") -> Sale | L915: Paypal
A916: 5914 | B916: 31 | C916: =IFERROR(_xlfn.XLOOKUP(B916, Customers_raw!A:A, Customers_raw!B:B), "Unknown Customer") -> Nancy Harris | D916: 45818 | E916: =TEXT(D:D,"YYYY-MM") -> 2025-06 | F916: Memory Foam Pillow | G916: Bedding | H916: 2 | I916: 29 | J916: =H916*I916 -> 58 | K916: =IF(H916<0,"Return","Sale") -> Sale | L916: Credit Card
A917: 5915 | B917: 51 | C917: =IFERROR(_xlfn.XLOOKUP(B917, Customers_raw!A:A, Customers_raw!B:B), "Unknown Customer") -> Patricia Hernandez | D917: 45695 | E917: =TEXT(D:D,"YYYY-MM") -> 2025-02 | F917: Ceramic Mug Set | G917: Kitchen | H917: 3 | I917: 23.742857 | J917: =H917*I917 -> 71.228571 | K917: =IF(H917<0,"Return","Sale") -> Sale | L917: Paypal
... A987: 5985 | B987: 106 | C987: =IFERROR(_xlfn.XLOOKUP(B987, Customers_raw!A:A, Customers_raw!B:B), "Unknown Customer") -> Thomas Lopez | D987: 45995 | E987: =TEXT(D:D,"YYYY-MM") -> 2025-12 | F987: Memory Foam Pillow | G987: Bedding | H987: -2 | I987: 29 | J987: =H987*I987 -> -58 | K987: =IF(H987<0,"Return","Sale") -> Return | L987: Credit Card
A988: 5986 | B988: Unknown | C988: =IFERROR(_xlfn.XLOOKUP(B988, Customers_raw!A:A, Customers_raw!B:B), "Unknown Customer") -> Unknown Customer | D988: 45888 | E988: =TEXT(D:D,"YYYY-MM") -> 2025-08 | F988: Cutting Board | G988: Kitchen | H988: 1 | I988: 16 | J988: =H988*I988 -> 16 | K988: =IF(H988<0,"Return","Sale") -> Sale | L988: Paypal
A989: 5987 | B989: 30 | C989: =IFERROR(_xlfn.XLOOKUP(B989, Customers_raw!A:A, Customers_raw!B:B), "Unknown Customer") -> Sandra Taylor | D989: 45948 | E989: =TEXT(D:D,"YYYY-MM") -> 2025-10 | F989: Cotton Bedsheet Set | G989: Bedding | H989: 1 | I989: 52 | J989: =H989*I989 -> 52 | K989: =IF(H989<0,"Return","Sale") -> Sale | L989: Debit Card
A990: 5988 | B990: 70 | C990: =IFERROR(_xlfn.XLOOKUP(B990, Customers_raw!A:A, Customers_raw!B:B), "Unknown Customer") -> Karen Perez | D990: 45906 | E990: =TEXT(D:D,"YYYY-MM") -> 2025-09 | F990: Throw Pillow | G990: Home Decor | H990: 3 | I990: 19 | J990: =H990*I990 -> 57 | K990: =IF(H990<0,"Return","Sale") -> Sale | L990: Paypal
A991: 5989 | B991: 5 | C991: =IFERROR(_xlfn.XLOOKUP(B991, Customers_raw!A:A, Customers_raw!B:B), "Unknown Customer") -> Joshua Martin | D991: 45722 | E991: =TEXT(D:D,"YYYY-MM") -> 2025-03 | F991: Cutting Board | G991: Kitchen | H991: 2 | I991: 22 | J991: =H991*I991 -> 44 | K991: =IF(H991<0,"Return","Sale") -> Sale | L991: Paypal
A992: 5990 | B992: 35 | C992: =IFERROR(_xlfn.XLOOKUP(B992, Customers_raw!A:A, Customers_raw!B:B), "Unknown Customer") -> Richard Clark | D992: 45734 | E992: =TEXT(D:D,"YYYY-MM") -> 2025-03 | F992: String Lights | G992: Lighting | H992: 3 | I992: 18 | J992: =H992*I992 -> 54 | K992: =IF(H992<0,"Return","Sale") -> Sale | L992: Debit Card
A993: 5991 | B993: 66 | C993: =IFERROR(_xlfn.XLOOKUP(B993, Customers_raw!A:A, Customers_raw!B:B), "Unknown Customer") -> Barbara Anderson | D993: 45688 | E993: =TEXT(D:D,"YYYY-MM") -> 2025-01 | F993: Memory Foam Pillow | G993: Bedding | H993: 1 | I993: 35 | J993: =H993*I993 -> 35 | K993: =IF(H993<0,"Return","Sale") -> Sale | L993: Debit Card
A994: 5992 | B994: 74 | C994: =IFERROR(_xlfn.XLOOKUP(B994, Customers_raw!A:A, Customers_raw!B:B), "Unknown Customer") -> Betty Moore | D994: 45984 | E994: =TEXT(D:D,"YYYY-MM") -> 2025-11 | F994: Ceramic Mug Set | G994: Kitchen | H994: 3 | I994: 21 | J994: =H994*I994 -> 63 | K994: =IF(H994<0,"Return","Sale") -> Sale | L994: Credit Card
A995: 5993 | B995: 15 | C995: =IFERROR(_xlfn.XLOOKUP(B995, Customers_raw!A:A, Customers_raw!B:B), "Unknown Customer") -> Jennifer Rodriguez | D995: 45994 | E995: =TEXT(D:D,"YYYY-MM") -> 2025-12 | F995: Table Lamp | G995: Lighting | H995: 1 | I995: 45 | J995: =H995*I995 -> 45 | K995: =IF(H995<0,"Return","Sale") -> Sale | L995: Credit Card
A996: 5994 | B996: 70 | C996: =IFERROR(_xlfn.XLOOKUP(B996, Customers_raw!A:A, Customers_raw!B:B), "Unknown Customer") -> Karen Perez | D996: 45845 | E996: =TEXT(D:D,"YYYY-MM") -> 2025-07 | F996: Floor Lamp | G996: Lighting | H996: 1 | I996: 89 | J996: =H996*I996 -> 89 | K996: =IF(H996<0,"Return","Sale") -> Sale | L996: Debit Card
A997: 5995 | B997: 32 | C997: =IFERROR(_xlfn.XLOOKUP(B997, Customers_raw!A:A, Customers_raw!B:B), "Unknown Customer") -> Kimberly Lopez | D997: 45964 | E997: =TEXT(D:D,"YYYY-MM") -> 2025-11 | F997: String Lights | G997: Lighting | H997: 1 | I997: 18 | J997: =H997*I997 -> 18 | K997: =IF(H997<0,"Return","Sale") -> Sale | L997: Paypal
A998: 5996 | B998: 3 | C998: =IFERROR(_xlfn.XLOOKUP(B998, Customers_raw!A:A, Customers_raw!B:B), "Unknown Customer") -> Anthony Williams | D998: 45875 | E998: =TEXT(D:D,"YYYY-MM") -> 2025-08 | F998: Wool Blanket | G998: Bedding | H998: 3 | I998: 67 | J998: =H998*I998 -> 201 | K998: =IF(H998<0,"Return","Sale") -> Sale | L998: Credit Card
A999: 5997 | B999: 61 | C999: =IFERROR(_xlfn.XLOOKUP(B999, Customers_raw!A:A, Customers_raw!B:B), "Unknown Customer") -> Jennifer Harris | D999: 45994 | E999: =TEXT(D:D,"YYYY-MM") -> 2025-12 | F999: Memory Foam Pillow | G999: Bedding | H999: 2 | I999: 32 | J999: =H999*I999 -> 64 | K999: =IF(H999<0,"Return","Sale") -> Sale | L999: Paypal
A1000: 5998 | B1000: 16 | C1000: =IFERROR(_xlfn.XLOOKUP(B1000, Customers_raw!A:A, Customers_raw!B:B), "Unknown Customer") -> Karen Perez | D1000: 45821 | E1000: =TEXT(D:D,"YYYY-MM") -> 2025-06 | F1000: Ceramic Vase | G1000: Home Decor | H1000: 2 | I1000: 31 | J1000: =H1000*I1000 -> 62 | K1000: =IF(H1000<0,"Return","Sale") -> Sale | L1000: Debit Card
... A1079: 6077 | B1079: 83 | C1079: =IFERROR(_xlfn.XLOOKUP(B1079, Customers_raw!A:A, Customers_raw!B:B), "Unknown Customer") -> Mary Martinez | D1079: 45993 | E1079: =TEXT(D:D,"YYYY-MM") -> 2025-12 | F1079: Cutting Board | G1079: Kitchen | H1079: 2 | I1079: 16 | J1079: =H1079*I1079 -> 32 | K1079: =IF(H1079<0,"Return","Sale") -> Sale | L1079: Paypal
A1080: 6078 | B1080: Unknown | C1080: =IFERROR(_xlfn.XLOOKUP(B1080, Customers_raw!A:A, Customers_raw!B:B), "Unknown Customer") -> Unknown Customer | D1080: 45757 | E1080: =TEXT(D:D,"YYYY-MM") -> 2025-04 | F1080: Ceramic Vase | G1080: Home Decor | H1080: 1 | I1080: 28 | J1080: =H1080*I1080 -> 28 | K1080: =IF(H1080<0,"Return","Sale") -> Sale | L1080: Paypal
A1081: 6079 | B1081: 98 | C1081: =IFERROR(_xlfn.XLOOKUP(B1081, Customers_raw!A:A, Customers_raw!B:B), "Unknown Customer") -> Karen Williams | D1081: 45964 | E1081: =TEXT(D:D,"YYYY-MM") -> 2025-11 | F1081: String Lights | G1081: Lighting | H1081: 3 | I1081: 18 | J1081: =H1081*I1081 -> 54 | K1081: =IF(H1081<0,"Return","Sale") -> Sale | L1081: Debit Card
A1082: 6080 | B1082: 102 | C1082: =IFERROR(_xlfn.XLOOKUP(B1082, Customers_raw!A:A, Customers_raw!B:B), "Unknown Customer") -> Ashley Wilson | D1082: 45943 | E1082: =TEXT(D:D,"YYYY-MM") -> 2025-10 | F1082: Ceramic Mug Set | G1082: Kitchen | H1082: 1 | I1082: 21 | J1082: =H1082*I1082 -> 21 | K1082: =IF(H1082<0,"Return","Sale") -> Sale | L1082: Debit Card
A1083: 6081 | B1083: 101 | C1083: =IFERROR(_xlfn.XLOOKUP(B1083, Customers_raw!A:A, Customers_raw!B:B), "Unknown Customer") -> David Lee | D1083: 45806 | E1083: =TEXT(D:D,"YYYY-MM") -> 2025-05 | F1083: Table Lamp | G1083: Lighting | H1083: 2 | I1083: 42 | J1083: =H1083*I1083 -> 84 | K1083: =IF(H1083<0,"Return","Sale") -> Sale | L1083: Credit Card
A1084: 6082 | B1084: 42 | C1084: =IFERROR(_xlfn.XLOOKUP(B1084, Customers_raw!A:A, Customers_raw!B:B), "Unknown Customer") -> Jennifer Harris | D1084: 45697 | E1084: =TEXT(D:D,"YYYY-MM") -> 2025-02 | F1084: Cutting Board | G1084: Kitchen | H1084: 1 | I1084: 19 | J1084: =H1084*I1084 -> 19 | K1084: =IF(H1084<0,"Return","Sale") -> Sale | L1084: Paypal
A1085: 6083 | B1085: 27 | C1085: =IFERROR(_xlfn.XLOOKUP(B1085, Customers_raw!A:A, Customers_raw!B:B), "Unknown Customer") -> Nancy Lee | D1085: 45883 | E1085: =TEXT(D:D,"YYYY-MM") -> 2025-08 | F1085: Ceramic Mug Set | G1085: Kitchen | H1085: 2 | I1085: 24 | J1085: =H1085*I1085 -> 48 | K1085: =IF(H1085<0,"Return","Sale") -> Sale | L1085: Paypal
A1086: 6084 | B1086: 27 | C1086: =IFERROR(_xlfn.XLOOKUP(B1086, Customers_raw!A:A, Customers_raw!B:B), "Unknown Customer") -> Nancy Lee | D1086: 45929 | E1086: =TEXT(D:D,"YYYY-MM") -> 2025-09 | F1086: Wall Mirror | G1086: Home Decor | H1086: 2 | I1086: 65 | J1086: =H1086*I1086 -> 130 | K1086: =IF(H1086<0,"Return","Sale") -> Sale | L1086: Credit Card
A1087: 6085 | B1087: 18 | C1087: =IFERROR(_xlfn.XLOOKUP(B1087, Customers_raw!A:A, Customers_raw!B:B), "Unknown Customer") -> Susan Sanchez | D1087: 45681 | E1087: =TEXT(D:D,"YYYY-MM") -> 2025-01 | F1087: Cutting Board | G1087: Kitchen | H1087: 1 | I1087: 22 | J1087: =H1087*I1087 -> 22 | K1087: =IF(H1087<0,"Return","Sale") -> Sale | L1087: Credit Card
A1088: 6086 | B1088: 56 | C1088: =IFERROR(_xlfn.XLOOKUP(B1088, Customers_raw!A:A, Customers_raw!B:B), "Unknown Customer") -> Mark Hernandez | D1088: 45724 | E1088: =TEXT(D:D,"YYYY-MM") -> 2025-03 | F1088: Cutting Board | G1088: Kitchen | H1088: 2 | I1088: 22 | J1088: =H1088*I1088 -> 44 | K1088: =IF(H1088<0,"Return","Sale") -> Sale | L1088: Paypal
A1089: 6087 | B1089: 25 | C1089: =IFERROR(_xlfn.XLOOKUP(B1089, Customers_raw!A:A, Customers_raw!B:B), "Unknown Customer") -> Emily Wilson | D1089: 45903 | E1089: =TEXT(D:D,"YYYY-MM") -> 2025-09 | F1089: Cutting Board | G1089: Kitchen | H1089: 1 | I1089: 19 | J1089: =H1089*I1089 -> 19 | K1089: =IF(H1089<0,"Return","Sale") -> Sale | L1089: Debit Card
A1090: 6088 | B1090: 106 | C1090: =IFERROR(_xlfn.XLOOKUP(B1090, Customers_raw!A:A, Customers_raw!B:B), "Unknown Customer") -> Thomas Lopez | D1090: 45720 | E1090: =TEXT(D:D,"YYYY-MM") -> 2025-03 | F1090: String Lights | G1090: Lighting | H1090: 2 | I1090: 18 | J1090: =H1090*I1090 -> 36 | K1090: =IF(H1090<0,"Return","Sale") -> Sale | L1090: Debit Card
A1091: 6089 | B1091: 86 | C1091: =IFERROR(_xlfn.XLOOKUP(B1091, Customers_raw!A:A, Customers_raw!B:B), "Unknown Customer") -> Steven Jones | D1091: 45868 | E1091: =TEXT(D:D,"YYYY-MM") -> 2025-07 | F1091: Memory Foam Pillow | G1091: Bedding | H1091: 1 | I1091: 32 | J1091: =H1091*I1091 -> 32 | K1091: =IF(H1091<0,"Return","Sale") -> Sale | L1091: Debit Card
A1092: 6090 | B1092: 79 | C1092: =IFERROR(_xlfn.XLOOKUP(B1092, Customers_raw!A:A, Customers_raw!B:B), "Unknown Customer") -> Nancy Jackson | D1092: 45877 | E1092: =TEXT(D:D,"YYYY-MM") -> 2025-08 | F1092: Ceramic Mug Set | G1092: Kitchen | H1092: 1 | I1092: 24 | J1092: =H1092*I1092 -> 24 | K1092: =IF(H1092<0,"Return","Sale") -> Sale | L1092: Paypal
... A1301: 6299 | B1301: 109 | C1301: =IFERROR(_xlfn.XLOOKUP(B1301, Customers_raw!A:A, Customers_raw!B:B), "Unknown Customer") -> Richard Sanchez | D1301: 45743 | E1301: =TEXT(D:D,"YYYY-MM") -> 2025-03 | F1301: Cotton Bedsheet Set | G1301: Bedding | H1301: -1 | I1301: 52 | J1301: =H1301*I1301 -> -52 | K1301: =IF(H1301<0,"Return","Sale") -> Return | L1301: Paypal

Sheet Customers_raw
A1: Customer_id | B1: Customer_Name | C1: Email | D1: City | E1: Signup_Date
A2: 1 | B2: Christopher Jones | C2: Christopher.Jones75@Gmail.Com | D2: Seattle | E2: 45341
A3: 2 | B3: Michael Lopez | C3: Michael.Lopez39@Gmail.Com | D3: Austin | E3: 45511
A4: 3 | B4: Anthony Williams | C4: Unknown | D4: Chicago | E4: 45856
A5: 4 | B5: Joshua Brown | C5: Joshua.Brown597@Gmail.Com | D5: Chicago | E5: 45934
A6: 5 | B6: Joshua Martin | C6: Joshua.Martin48@Gmail.Com | D6: Seattle | E6: 45518
A7: 6 | B7: David Martinez | C7: David.Martinez121@Gmail.Com | D7: Seattle | E7: 45845
A8: 7 | B8: Emily Ramirez | C8: Emily.Ramirez585@Gmail.Com | D8: Portland | E8: 45887
A9: 8 | B9: Lisa Brown | C9: Lisa.Brown634@Gmail.Com | D9: Denver | E9: 45353
A10: 9 | B10: Andrew Anderson | C10: Andrew.Anderson946@Gmail.Com | D10: Atlanta | E10: 45891
A11: 10 | B11: Karen Davis | C11: Karen.Davis589@Gmail.Com | D11: Portland | E11: 45375
A12: 11 | B12: Ashley Robinson | C12: Ashley.Robinson624@Gmail.Com | D12: Atlanta | E12: 45586
A13: 12 | B13: Linda Moore | C13: Linda.Moore156@Gmail.Com | D13: Seattle | E13: 45642
... A111: 110 | B111: Betty Walker | C111: Betty.Walker51@Gmail.Com | D111: Chicago | E111: 45374

Sheet Pivot_Table
A1: Monthly Revenue by Category
I2: Monthly Sales – 2025
A3: Sum of Total_Price | B3: Column Labels
A4: Row Labels | B4: Bedding | C4: Home Decor | D4: Kitchen | E4: Lighting | F4: Grand Total | I4: Row Labels | J4: Sum of Total_Price
A5: 2025-01 | B5: 2575 | C5: 1336.1417 | D5: 1223.1905 | E5: 1539.6429 | F5: 6673.9751 | I5: 2025-01 | J5: 6673.9751
A6: 2025-02 | B6: 2271.7941 | C6: 2149.1472 | D6: 1311.7143 | E6: 2093 | F6: 7825.6556 | I6: 2025-02 | J6: 7825.6556
A7: 2025-03 | B7: 2264.8788 | C7: 1949 | D7: 1263.419 | E7: 2679.4327 | F7: 8156.7305 | I7: 2025-03 | J7: 8156.7305
A8: 2025-04 | B8: 1460.7941 | C8: 1740.3 | D8: 832.44762 | E8: 1723.2885 | F8: 5756.8302 | I8: 2025-04 | J8: 5756.8302
A9: 2025-05 | B9: 2065.0669 | C9: 1495.1 | D9: 876.13187 | E9: 2480.4327 | F9: 6916.7314 | I9: 2025-05 | J9: 6916.7314
A10: 2025-06 | B10: 1866 | C10: 1828 | D10: 1591.7143 | E10: 1934.7015 | F10: 7220.4158 | I10: 2025-06 | J10: 7220.4158
A11: 2025-07 | B11: 3014 | C11: 2042.2362 | D11: 1536.6762 | E11: 1936.988 | F11: 8529.9004 | I11: 2025-07 | J11: 8529.9004
A12: 2025-08 | B12: 1919 | C12: 1980.389 | D12: 1397 | E12: 2343.4544 | F12: 7639.8434 | I12: 2025-08 | J12: 7639.8434
A13: 2025-09 | B13: 2247.1546 | C13: 1234.1 | D13: 1015.1319 | E13: 1383 | F13: 5879.3865 | I13: 2025-09 | J13: 5879.3865
A14: 2025-10 | B14: 2378.4639 | C14: 1328.6545 | D14: 1660 | E14: 1947.5957 | F14: 7314.7142 | I14: 2025-10 | J14: 7314.7142
A15: 2025-11 | B15: 2529.7398 | C15: 1406 | D15: 1266 | E15: 3049 | F15: 8250.7398 | I15: 2025-11 | J15: 8250.7398
A16: 2025-12 | B16: 2368.5704 | C16: 1172.6727 | D16: 1557.1905 | E16: 1593.0217 | F16: 6691.4554 | I16: 2025-12 | J16: 6691.4554
A17: Grand Total | B17: 26960.463 | C17: 19661.741 | D17: 15530.616 | E17: 24703.558 | F17: 86856.378 | I17: Grand Total | J17: 86856.378
A37: Top 10 Customers by Total Spend
A39: Row Labels | B39: Sum of Total_Price
A40: Betty Johnson | B40: 1694.4173
A41: Betty Moore | B41: 1479
A42: Jennifer White | B42: 1649
A43: Joshua Martin | B43: 1686
A44: Karen Clark | B44: 1908.0945
A45: Karen Perez | B45: 2000
A46: Michael Lopez | B46: 1859.1417
A47: Michael Moore | B47: 1588
A48: Thomas Lopez | B48: 1559.4592
A49: Thomas Ramirez | B49: 1874.7309
A52: Return Rate (%)
A54: =COUNTIF(Orders_raw!K:K,"Return") / COUNTA(Orders_raw!K:K) -> 0.035357417
